code/job.slurm
code/main.py
code/opt.py
code/train.py
code/dataloader/__init__.py
code/dataloader/generic_data.py
code/model/__init__.py
code/model/net.py
code/utils/__init__.py
code/utils/utils.py
code/utils/vis_utils.py
param_opt-0.0.4.dist-info/LICENSE
param_opt-0.0.4.dist-info/METADATA
param_opt-0.0.4.dist-info/WHEEL
param_opt-0.0.4.dist-info/top_level.txt
param_opt-0.0.4.dist-info/RECORD
