Metadata-Version: 2.1
Name: param-opt
Version: 0.0.4
Summary: This repository features an ML approach toward estimating process parameters for production steps
Home-page: https://github.com/j-ehrhardt/p-opt
Author: Jonas Ehrhardt
License: MIT
Classifier: Development Status :: 3 - Alpha
Classifier: Intended Audience :: Developers
Classifier: License :: OSI Approved :: MIT License
Classifier: Programming Language :: Python :: 3.12
Requires-Python: >= 3.12
License-File: LICENSE
